sioba_websocket/__init__.py
sioba_websocket/interface/__init__.py
sioba_websocket-0.1.20250928.dist-info/WHEEL
sioba_websocket-0.1.20250928.dist-info/entry_points.txt
sioba_websocket-0.1.20250928.dist-info/METADATA
sioba_websocket-0.1.20250928.dist-info/RECORD
